LICENSE
README.md
setup.py
blockchain/__init__.py
blockchain/constants.py
blockchain/search_utils.py
blockchain/token_utils.py
common/__init__.py
common/secretmanager.py
common_utils/__init__.py
common_utils/chain_utils.py
common_utils/constants.py
common_utils/number_utils.py
common_utils/parser.py
common_utils/sqs_utils.py
common_utils/telegram_utils.py
common_utils/time_utils.py
common_utils/utils.py
cryptoowl.egg-info/PKG-INFO
cryptoowl.egg-info/SOURCES.txt
cryptoowl.egg-info/dependency_links.txt
cryptoowl.egg-info/requires.txt
cryptoowl.egg-info/top_level.txt
db/__init__.py
db/databases.py
experimentation/__init__.py
experimentation/experiments.py
security/__init__.py
security/constants.py
security/security.py