Metadata-Version: 2.4
Name: cryptoowl
Version: 0.1.13
Summary: A library, that stores commonly used code for different modules in the CryptoOwl application
Author: Cryptoowl
Author-email: cryptoowl.app@gmail.com
Classifier: Programming Language :: Python :: 3
Classifier: License :: OSI Approved :: MIT License
Classifier: Operating System :: OS Independent
License-File: LICENSE
Requires-Dist: pytz
Requires-Dist: boto3
Requires-Dist: PyMySQL
Requires-Dist: redis
Requires-Dist: botocore
Requires-Dist: setuptools
Requires-Dist: pymemcache
Requires-Dist: psycopg2-binary
Requires-Dist: requests
Requires-Dist: pydantic
Dynamic: author
Dynamic: author-email
Dynamic: classifier
Dynamic: description
Dynamic: license-file
Dynamic: requires-dist
Dynamic: summary
